SmartSecurityPy/__init__.py
SmartSecurityPy/crypto.py
SmartSecurityPy/hasher.py
SmartSecurityPy/jwt_handler.py
SmartSecurityPy/password_validator.py
smartsecuritypy-1.0.0.dist-info/licenses/LICENSE
tests/__init__.py
tests/test_crypto.py
tests/test_hasher.py
tests/test_jwt_handler.py
tests/test_password_validator.py
smartsecuritypy-1.0.0.dist-info/METADATA
smartsecuritypy-1.0.0.dist-info/WHEEL
smartsecuritypy-1.0.0.dist-info/top_level.txt
smartsecuritypy-1.0.0.dist-info/RECORD
