Metadata-Version: 2.4
Name: SmartSecurityPy
Version: 1.0.0
Summary: 🔐 Biblioteca de utilidades para hash de senha, criptografia e JWT em Python
Author: Roberto Lima
Author-email: Roberto Lima <robertolima.izphera@gmail.com>
License: MIT
Project-URL: Homepage, https://github.com/robertolima-dev/SmartSecurityPy
Project-URL: Repository, https://github.com/robertolima-dev/SmartSecurityPy
Project-URL: Documentation, https://pypi.org/project/SmartSecurityPy/
Keywords: seguranca,criptografia,jwt,hash,senha
Classifier: Programming Language :: Python :: 3
Classifier: License :: OSI Approved :: MIT License
Classifier: Operating System :: OS Independent
Requires-Python: >=3.7
License-File: LICENSE
Requires-Dist: passlib[bcrypt]
Requires-Dist: cryptography
Requires-Dist: PyJWT
Dynamic: author
Dynamic: license-file
Dynamic: requires-python
